[
  {
    "id": "mfd613195",
    "userId": "u002",
    "type": "overdue_borrower",
    "uniqueKey": "overdue_borrower_b002",
    "borrowId": "b002",
    "instrumentId": "i001",
    "instrumentName": "雅马哈古典吉他 C40",
    "instrumentImage": "https://images.unsplash.com/photo-1510915361894-db8b60106cb1?w=400",
    "counterpartId": "u001",
    "counterpartName": "音乐小明",
    "counterpartAvatar": "https://api.dicebear.com/7.x/avataaars/svg?seed=xiaoming",
    "endDate": "2026-06-11",
    "overdueDays": 2,
    "title": "⚠️ 乐器已逾期",
    "content": "您借用的【雅马哈古典吉他 C40】已逾期 2 天，请尽快归还！",
    "read": false,
    "createdAt": "2026-06-12T21:10:30.425Z"
  },
  {
    "id": "m4a5ec90e",
    "userId": "u001",
    "type": "overdue_owner",
    "uniqueKey": "overdue_owner_b002",
    "borrowId": "b002",
    "instrumentId": "i001",
    "instrumentName": "雅马哈古典吉他 C40",
    "instrumentImage": "https://images.unsplash.com/photo-1510915361894-db8b60106cb1?w=400",
    "counterpartId": "u002",
    "counterpartName": "钢琴少女",
    "counterpartAvatar": "https://api.dicebear.com/7.x/avataaars/svg?seed=piano",
    "endDate": "2026-06-11",
    "overdueDays": 2,
    "title": "⚠️ 借出乐器已逾期",
    "content": "【钢琴少女】借用的【雅马哈古典吉他 C40】已逾期 2 天，请及时跟进归还事宜。",
    "read": false,
    "createdAt": "2026-06-12T21:10:30.425Z"
  },
  {
    "id": "mf5bfd561",
    "userId": "u004",
    "type": "upcoming_borrower",
    "uniqueKey": "upcoming_borrower_b003",
    "borrowId": "b003",
    "instrumentId": "i002",
    "instrumentName": "卡西欧电钢琴 PX-S1000",
    "instrumentImage": "https://images.unsplash.com/photo-1520523839897-bd0b52f945a0?w=400",
    "counterpartId": "u002",
    "counterpartName": "钢琴少女",
    "counterpartAvatar": "https://api.dicebear.com/7.x/avataaars/svg?seed=piano",
    "endDate": "2026-06-14",
    "remainingDays": 1,
    "title": "🔔 距归还还有 1 天",
    "content": "您借用的【卡西欧电钢琴 PX-S1000】还有 1 天到期，请提前做好归还准备。",
    "read": false,
    "createdAt": "2026-06-12T21:10:30.425Z"
  },
  {
    "id": "m2f055f82",
    "userId": "u002",
    "type": "upcoming_owner",
    "uniqueKey": "upcoming_owner_b003",
    "borrowId": "b003",
    "instrumentId": "i002",
    "instrumentName": "卡西欧电钢琴 PX-S1000",
    "instrumentImage": "https://images.unsplash.com/photo-1520523839897-bd0b52f945a0?w=400",
    "counterpartId": "u004",
    "counterpartName": "爵士鼓手",
    "counterpartAvatar": "https://api.dicebear.com/7.x/avataaars/svg?seed=drum",
    "endDate": "2026-06-14",
    "remainingDays": 1,
    "title": "🔔 距乐器归还还有 1 天",
    "content": "【爵士鼓手】借用的【卡西欧电钢琴 PX-S1000】还有 1 天到期，可适当提醒对方。",
    "read": false,
    "createdAt": "2026-06-12T21:10:30.425Z"
  },
  {
    "id": "m420a069d",
    "userId": "u003",
    "type": "upcoming_borrower",
    "uniqueKey": "upcoming_borrower_b004",
    "borrowId": "b004",
    "instrumentId": "i003",
    "instrumentName": "尤克里里 Uma 23寸",
    "instrumentImage": "https://images.unsplash.com/photo-1519689680058-324335c77eba?w=400",
    "counterpartId": "u001",
    "counterpartName": "音乐小明",
    "counterpartAvatar": "https://api.dicebear.com/7.x/avataaars/svg?seed=xiaoming",
    "endDate": "2026-06-15",
    "remainingDays": 2,
    "title": "🔔 距归还还有 2 天",
    "content": "您借用的【尤克里里 Uma 23寸】还有 2 天到期，请提前做好归还准备。",
    "read": false,
    "createdAt": "2026-06-12T21:10:30.425Z"
  },
  {
    "id": "m29c7add3",
    "userId": "u001",
    "type": "upcoming_owner",
    "uniqueKey": "upcoming_owner_b004",
    "borrowId": "b004",
    "instrumentId": "i003",
    "instrumentName": "尤克里里 Uma 23寸",
    "instrumentImage": "https://images.unsplash.com/photo-1519689680058-324335c77eba?w=400",
    "counterpartId": "u003",
    "counterpartName": "小提琴新手",
    "counterpartAvatar": "https://api.dicebear.com/7.x/avataaars/svg?seed=violin",
    "endDate": "2026-06-15",
    "remainingDays": 2,
    "title": "🔔 距乐器归还还有 2 天",
    "content": "【小提琴新手】借用的【尤克里里 Uma 23寸】还有 2 天到期，可适当提醒对方。",
    "read": false,
    "createdAt": "2026-06-12T21:10:30.425Z"
  }
]